diffusion/__init__.py
diffusion/callbacks/__init__.py
diffusion/callbacks/protocols.py
diffusion/callbacks/sampling.py
diffusion/configs/__init__.py
diffusion/configs/eval.py
diffusion/configs/protocols.py
diffusion/configs/train.py
diffusion/data/__init__.py
diffusion/data/diffusion.py
diffusion/data/sequence.py
diffusion/managers/__init__.py
diffusion/managers/base.py
diffusion/managers/ddpm.py
diffusion/managers/diffusion.py
diffusion/managers/latent.py
diffusion/managers/protocols.py
diffusion/managers/sde.py
diffusion/metrics/__init__.py
diffusion/metrics/iou.py
diffusion/metrics/lpips.py
diffusion/networks/__init__.py
diffusion/networks/builder.py
diffusion/networks/protocols.py
diffusion/networks/unet.py
diffusion/nn/__init__.py
diffusion/nn/attention.py
diffusion/nn/conv.py
diffusion/nn/diffusion/__init__.py
diffusion/nn/diffusion/ddpm.py
diffusion/nn/diffusion/diffusion.py
diffusion/nn/diffusion/fast_sampling.py
diffusion/nn/diffusion/latent.py
diffusion/nn/diffusion/protocols.py
diffusion/nn/diffusion/sde.py
diffusion/nn/embeddings.py
diffusion/nn/norm.py
diffusion/optim/__init__.py
diffusion/optim/ema.py
diffusion/scheduling/__init__.py
diffusion/scheduling/scheduler.py
diffusion/scheduling/space.py
diffusion/sde/__init__.py
diffusion/sde/base.py
diffusion/sde/loader.py
diffusion/sde/protocols.py
diffusion/sde/ve.py
diffusion/sde/vp.py
diffusion/version.py
torchmanager_diffusion-1.2.1.dist-info/METADATA
torchmanager_diffusion-1.2.1.dist-info/WHEEL
torchmanager_diffusion-1.2.1.dist-info/licenses/LICENSE
torchmanager_diffusion-1.2.1.dist-info/RECORD
