Metadata-Version: 2.4
Name: torchmanager-diffusion
Version: 1.2.1
Summary: Torchmanager Implementation for Diffusion Model (v1.2.1)
License-File: LICENSE
Author: Kison Ho
Author-email: unfit-gothic.0q@icloud.com
Requires-Python: >=3.10,<4.0
Classifier: Programming Language :: Python :: 3
Classifier: Programming Language :: Python :: 3.10
Classifier: Programming Language :: Python :: 3.11
Classifier: Programming Language :: Python :: 3.12
Classifier: Programming Language :: Python :: 3.13
Classifier: Programming Language :: Python :: 3.14
Requires-Dist: einops
Requires-Dist: lpips
Requires-Dist: torchmanager (>=1.4,<2.0)
